signalzero_sdk/__init__.py
signalzero_sdk/client.py
signalzero_sdk/errors.py
signalzero_sdk/py.typed
signalzero_sdk/types.py
signalzero_sdk/version.py
signalzero_sdk-0.1.0.dist-info/METADATA
signalzero_sdk-0.1.0.dist-info/WHEEL
signalzero_sdk-0.1.0.dist-info/top_level.txt
signalzero_sdk-0.1.0.dist-info/RECORD
