Metadata-Version: 2.4
Name: signalzero-sdk
Version: 0.1.0
Summary: Official Python SDK for SIGNAL.ZERO
Author: SIGNAL.ZERO
License: UNLICENSED
Project-URL: Homepage, https://www.signalzero.ink
Project-URL: Documentation, https://www.signalzero.ink/doc
Project-URL: OpenAPI, https://www.signalzero.ink/openapi.json
Keywords: signalzero,signal-zero,web3,api,sdk
Classifier: Development Status :: 3 - Alpha
Classifier: Intended Audience :: Developers
Classifier: License :: Other/Proprietary License
Classifier: Programming Language :: Python :: 3
Classifier: Programming Language :: Python :: 3 :: Only
Classifier: Programming Language :: Python :: 3.9
Classifier: Programming Language :: Python :: 3.10
Classifier: Programming Language :: Python :: 3.11
Classifier: Programming Language :: Python :: 3.12
Classifier: Typing :: Typed
Requires-Python: >=3.9
Requires-Dist: httpx<1,>=0.26
Provides-Extra: dev
Requires-Dist: pytest>=7; extra == "dev"
